[
  {
    "full_name": "electron/electronjs.org",
    "stargazers_count": 1272,
    "open_issues_count": 77,
    "forks_count": 644
  },
  {
    "full_name": "bdougie/git-twitch",
    "stargazers_count": 9,
    "open_issues_count": 0,
    "forks_count": 2
  },
  {
    "full_name": "open-sauced/open-sauced",
    "stargazers_count": 284,
    "open_issues_count": 25,
    "forks_count": 79
  },
  {
    "full_name": "mui-org/material-ui",
    "stargazers_count": 61778,
    "open_issues_count": 441,
    "forks_count": 18617
  },
  {
    "full_name": "Gruntfuggly/todo-tree",
    "stargazers_count": 511,
    "open_issues_count": 31,
    "forks_count": 53
  },
  {
    "full_name": "gatsbyjs/gatsby",
    "stargazers_count": 47503,
    "open_issues_count": 662,
    "forks_count": 8955
  }
]